{
    "CLI_package_name": "certora-cli",
    "CLI_version": "7.14.2",
    "branch": "certora",
    "certora_ci_client": null,
    "conf": {
        "files": [
            "contracts/NFTlendingBorrowing.sol"
        ],
        "hashing_length_bound": "128",
        "loop_iter": "3",
        "msg": "Verification of NFTLendingBorrowing",
        "multi_assert_check": true,
        "nondet_difficult_funcs": true,
        "optimistic_fallback": true,
        "optimistic_hashing": true,
        "optimistic_loop": true,
        "optimistic_summary_recursion": true,
        "packages": [
            "@openzeppelin=node_modules/@openzeppelin"
        ],
        "process": "emv",
        "rule_sanity": "basic",
        "send_only": true,
        "solc_optimize": "1000000",
        "solc_via_ir": true,
        "summary_recursion_limit": "300",
        "verify": "NFTlendingBorrowing:certora/NFTlendingBorrowing.spec"
    },
    "conf_path": null,
    "cwd_relative": ".",
    "dirty": true,
    "group_id": null,
    "main_spec": "certora/NFTlendingBorrowing.spec",
    "origin": "https://github.com/Pandora-Finance/aconomy-contract.git",
    "python_version": "3.10.12",
    "raw_args": [
        "/home/dell/.local/bin/certoraRun",
        "contracts/NFTlendingBorrowing.sol",
        "--verify",
        "NFTlendingBorrowing:certora/NFTlendingBorrowing.spec",
        "--optimistic_loop",
        "--optimistic_summary_recursion",
        "--optimistic_fallback",
        "--summary_recursion_limit",
        "300",
        "--nondet_difficult_funcs",
        "--optimistic_hashing",
        "--hashing_length_bound",
        "128",
        "--loop_iter",
        "3",
        "--solc_via_ir",
        "--solc_optimize",
        "1000000",
        "--msg",
        "Verification of NFTLendingBorrowing",
        "--packages",
        "@openzeppelin=node_modules/@openzeppelin",
        "--multi_assert_check",
        "--rule_sanity",
        "--send_only"
    ],
    "revision": "34d8da1e56f7b036eb5a74146109faf87bc1eaf5",
    "timestamp": "1725489246.996678"
}